pyromaths_qt-21.8-nspkg.pth
pyromaths/qt/__init__.py
pyromaths/qt/__main__.py
pyromaths/qt/config.py
pyromaths/qt/directories.py
pyromaths/qt/testenv.py
pyromaths/qt/version.py
pyromaths/qt/data/images/pyromaths-banniere.png
pyromaths/qt/data/images/pyromaths.ico
pyromaths/qt/data/images/pyromaths.png
pyromaths/qt/data/images/whatsthis.png
pyromaths/qt/data/locale/TRADUIRE.md
pyromaths/qt/data/locale/pyromaths.pot
pyromaths/qt/data/locale/traductibles
pyromaths/qt/data/locale/ca@valencia/LC_MESSAGES/pyromaths.mo
pyromaths/qt/data/locale/ca@valencia/LC_MESSAGES/pyromaths.po
pyromaths/qt/data/locale/en/LC_MESSAGES/pyromaths.mo
pyromaths/qt/data/locale/en/LC_MESSAGES/pyromaths.po
pyromaths/qt/data/locale/es/LC_MESSAGES/pyromaths.mo
pyromaths/qt/data/locale/es/LC_MESSAGES/pyromaths.po
pyromaths/qt/data/locale/pl/LC_MESSAGES/pyromaths.mo
pyromaths/qt/data/locale/pl/LC_MESSAGES/pyromaths.po
pyromaths_qt-21.8.data/data/pyromaths/qt/data/images/pyromaths-banniere.png
pyromaths_qt-21.8.data/data/pyromaths/qt/data/images/pyromaths.ico
pyromaths_qt-21.8.data/data/pyromaths/qt/data/images/pyromaths.png
pyromaths_qt-21.8.data/data/pyromaths/qt/data/images/whatsthis.png
pyromaths_qt-21.8.data/data/pyromaths/qt/data/locale/TRADUIRE.md
pyromaths_qt-21.8.data/data/pyromaths/qt/data/locale/pyromaths.pot
pyromaths_qt-21.8.data/data/pyromaths/qt/data/locale/traductibles
pyromaths_qt-21.8.data/data/pyromaths/qt/data/locale/ca@valencia/LC_MESSAGES/pyromaths.mo
pyromaths_qt-21.8.data/data/pyromaths/qt/data/locale/ca@valencia/LC_MESSAGES/pyromaths.po
pyromaths_qt-21.8.data/data/pyromaths/qt/data/locale/en/LC_MESSAGES/pyromaths.mo
pyromaths_qt-21.8.data/data/pyromaths/qt/data/locale/en/LC_MESSAGES/pyromaths.po
pyromaths_qt-21.8.data/data/pyromaths/qt/data/locale/es/LC_MESSAGES/pyromaths.mo
pyromaths_qt-21.8.data/data/pyromaths/qt/data/locale/es/LC_MESSAGES/pyromaths.po
pyromaths_qt-21.8.data/data/pyromaths/qt/data/locale/pl/LC_MESSAGES/pyromaths.mo
pyromaths_qt-21.8.dist-info/AUTHORS
pyromaths_qt-21.8.dist-info/COPYING
pyromaths_qt-21.8.dist-info/LICENSE
pyromaths_qt-21.8.dist-info/METADATA
pyromaths_qt-21.8.dist-info/WHEEL
pyromaths_qt-21.8.dist-info/entry_points.txt
pyromaths_qt-21.8.dist-info/namespace_packages.txt
pyromaths_qt-21.8.dist-info/top_level.txt
pyromaths_qt-21.8.dist-info/RECORD
