Metadata-Version: 2.1
Name: pyromaths-qt
Version: 21.8
Summary: Create maths exercises in LaTeX and PDF format -- QT client
Home-page: http://www.pyromaths.org
Author: Jérôme Ortais
Author-email: jerome.ortais@pyromaths.org
License: GPLv2
Download-URL: http://www.pyromaths.org/telecharger/
Project-URL: Documentation, http://pyromaths.readthedocs.org
Project-URL: Download, https://www.pyromaths.org/telecharger/
Project-URL: Forum, https://forum.pyromaths.org
Project-URL: Sources, https://framagit.org/pyromaths/pyromaths
Project-URL: Tickets, https://framagit.org/pyromaths/pyromaths/issues
Project-URL: Version en ligne, http://enligne.pyromaths.org/
Keywords: exercices math latex school
Platform: UNKNOWN
Classifier: Development Status :: 5 - Production/Stable
Classifier: Intended Audience :: Education
Classifier: Environment :: X11 Applications :: Qt
Classifier: Environment :: MacOS X
Classifier: Environment :: Win32 (MS Windows)
Classifier: License :: OSI Approved :: GNU General Public License v3 or later (GPLv3+)
Classifier: Operating System :: OS Independent
Classifier: Programming Language :: Python
Classifier: Programming Language :: Python :: 3
Classifier: Programming Language :: Python :: 3.5
Classifier: Programming Language :: Python :: 3.6
Classifier: Topic :: Software Development :: Code Generators
Classifier: Topic :: Text Processing :: Markup :: LaTeX
Requires-Dist: PyQt5 (>=5.10)
Requires-Dist: lxml (>=4.2.1)
Requires-Dist: pyromaths (>=18.7)
